CodeEntropy/__init__.py
CodeEntropy/dihedral_tools.py
CodeEntropy/entropy.py
CodeEntropy/group_molecules.py
CodeEntropy/levels.py
CodeEntropy/main.py
CodeEntropy/mda_universe_operations.py
CodeEntropy/run.py
CodeEntropy/config/__init__.py
CodeEntropy/config/arg_config_manager.py
CodeEntropy/config/data_logger.py
CodeEntropy/config/logging_config.py
codeentropy-1.0.7.dist-info/entry_points.txt
codeentropy-1.0.7.dist-info/licenses/LICENSE
codeentropy-1.0.7.dist-info/WHEEL
codeentropy-1.0.7.dist-info/METADATA
codeentropy-1.0.7.dist-info/RECORD
