Metadata-Version: 2.4
Name: CodeEntropy
Version: 1.0.7
Summary: CodeEntropy is a Python package for computing the configurational entropy of macromolecular systems using forces sampled from molecular dynamics (MD) simulations. It implements the multiscale cell correlation method to provide accurate and efficient entropy estimates, supporting a wide range of applications in molecular simulation and statistical mechanics.
Keywords: entropy,macromolecular systems,MD simulation
Author-email: Arghya 'Argo' Chakravorty <arghyac@umich.edu>, Donald Chung-HK <donald.chung@stfc.ac.uk>, Sarah Fegan <sarah.fegan@stfc.ac.uk>, James Gebbie-Rayet <james.gebbie@stfc.ac.uk>, Sarah Harris <sarah.harris@sheffield.ac.uk>, Richard Henchman <rhen7213@uni.sydney.edu.au>, Jonathan Higham <j.higham4@lancaster.ac.uk>, Jas Kalayan <jas.kalayan@stfc.ac.uk>, Ioana Papa <iapapa1@sheffield.ac.uk>
Maintainer-email: Harry Swift <harry.swift@stfc.ac.uk>
Requires-Python: >=3.11
Classifier: Programming Language :: Python
Classifier: Programming Language :: Python :: 3.11
Classifier: Programming Language :: Python :: 3.12
Classifier: Programming Language :: Python :: 3.13
Classifier: Programming Language :: Python :: 3.14
Classifier: Intended Audience :: Science/Research
Classifier: License :: OSI Approved :: MIT License
Classifier: Natural Language :: English
Classifier: Development Status :: 5 - Production/Stable
License-File: LICENSE
Requires-Dist: numpy>=2.3,<3.0
Requires-Dist: mdanalysis>=2.10,<3.0
Requires-Dist: pandas>=2.3,<3.0
Requires-Dist: psutil>=7.1,<8.0
Requires-Dist: PyYAML>=6.0,<7.0
Requires-Dist: python-json-logger>=4.0,<5.0
Requires-Dist: rich>=14.2,<15.0
Requires-Dist: art>=6.5,<7.0
Requires-Dist: waterEntropy>=2,<2.1
Requires-Dist: requests>=2.32,<3.0
Requires-Dist: sphinx>=7.0,<8.0 ; extra == "docs"
Requires-Dist: nbsphinx>=0.9,<1.0 ; extra == "docs"
Requires-Dist: sphinx_rtd_theme>=3,<3.1 ; extra == "docs"
Requires-Dist: sphinxcontrib-contentui>=0.2,<1.0 ; extra == "docs"
Requires-Dist: sphinxcontrib-details-directive>=0.1,<1.0 ; extra == "docs"
Requires-Dist: sphinx_copybutton>=0.5,<1.0 ; extra == "docs"
Requires-Dist: furo>=2025.0,<2026.0 ; extra == "docs"
Requires-Dist: markupsafe>=3.0,<4.0 ; extra == "docs"
Requires-Dist: pre-commit>=4.5,<5.0 ; extra == "pre-commit"
Requires-Dist: pylint>=4.0,<5.0 ; extra == "pre-commit"
Requires-Dist: pytest>=9.0,<10.0 ; extra == "testing"
Requires-Dist: pytest-cov>=7.0,<8.0 ; extra == "testing"
Requires-Dist: pytest-sugar>=1.1,<2.0 ; extra == "testing"
Project-URL: Documentation, https://codeentropy.readthedocs.io
Project-URL: Homepage, https://ccpbiosim.github.io/CodeEntropy/
Project-URL: Repository, https://github.com/CCPBioSim/CodeEntropy
Provides-Extra: docs
Provides-Extra: pre-commit
Provides-Extra: testing
